extratyping/__init__.py
extratyping/primitive.py
extratyping-1.0.0.dist-info/LICENSE
extratyping-1.0.0.dist-info/METADATA
extratyping-1.0.0.dist-info/WHEEL
extratyping-1.0.0.dist-info/top_level.txt
extratyping-1.0.0.dist-info/RECORD
